catpy/__init__.py
catpy/author.py
catpy/client.py
catpy/compat.py
catpy/enums.py
catpy/exceptions.py
catpy/image.py
catpy/spatial.py
catpy/stacks.py
catpy/url.py
catpy/util.py
catpy/version.py
catpy/applications/__init__.py
catpy/applications/base.py
catpy/applications/export.py
catpy/applications/morphology.py
catpy/applications/nameresolver.py
catpy/applications/relation_identifier.py
catpy/applications/stack.py
catpy-2020.9.3.dist-info/AUTHORS.rst
catpy-2020.9.3.dist-info/LICENSE
catpy-2020.9.3.dist-info/METADATA
catpy-2020.9.3.dist-info/WHEEL
catpy-2020.9.3.dist-info/top_level.txt
catpy-2020.9.3.dist-info/RECORD
