Metadata-Version: 2.1
Name: catpy
Version: 2020.9.3
Summary: Python client for the CATMAID API
Home-page: https://github.com/catmaid/catpy
Author: Andrew S. Champion
Author-email: andrew.champion@gmail.com
License: MIT license
Keywords: catpy catmaid neuron
Platform: UNKNOWN
Classifier: Development Status :: 2 - Pre-Alpha
Classifier: Intended Audience :: Developers
Classifier: Intended Audience :: Science/Research
Classifier: License :: OSI Approved :: MIT License
Classifier: Natural Language :: English
Classifier: Programming Language :: Python :: 3
Classifier: Programming Language :: Python :: 3.6
Classifier: Programming Language :: Python :: 3.7
Classifier: Programming Language :: Python :: 3.8
Classifier: Topic :: Scientific/Engineering :: Bio-Informatics
Requires-Dist: networkx (>=2.0)
Requires-Dist: numpy (>=1.12)
Requires-Dist: Pillow (>=5.0)
Requires-Dist: requests (>=2.14)
Requires-Dist: requests-futures (>=0.9)
